{"23":"#","2f":"/","-686fc27f":"#services","61642f31":"/about/","6851ce42":"tel:+41223191919","7adff995":"mailto:info@sawm.ch?subject=Contact","70df12fd":"https://www.google.com/maps/place/Bd+du+Th%C3%A9%C3%A2tre+2,+1204+Gen%C3%A8ve,+Switzerland/@46.2025498,6.1387794,17z/data=!3m1!4b1!4m6!3m5!1s0x478c652a029fa33d:0x6816afee8c47ed69!8m2!3d46.2025461!4d6.1413543!16s%2Fg%2F11c1x386tt?entry=ttu","-5b0dcf13":"/services/asset-management/","71cdd7a5":"/services/institutional-services/","-43fcb0f8":"/services/fund/","-43bd562b":"/services/digital-assets/","17a761b5":"mailto:info@sawm.ch?subject=contact","-2ff9dedf":"/assets/documents/best-execution-policy-for-silver-arrow-sa.pdf","-d4fd732":"https://anthonysalamin.ch","-3dc61c01":"mailto:info@sawm.ch?subject=Wealth%20Management%20Models","6d0994eb":"mailto:info@sawm.ch?subject=Strategic%20Planning","727c3bc3":"mailto:info@sawm.ch?subject=Digital%20Assets%20Advisory","-3e1b2e64":"mailto:info@sawm.ch?subject=Strategic%20Prime%20Funds","-7eb99368":"mailto:info@sawm.ch?subject=Treasury%20Management","28afe8ec":"mailto:info@sawm.ch?subject=Trade%20Finance%20Advisory%20%26%20Funding","710c0232":"/#services"}